settingscascade/__init__.py
settingscascade/element_schema.py
settingscascade/logger.py
settingscascade/manager.py
settingscascade/rule_set.py
settingscascade/selector.py
settingscascade/utils.py
settingscascade-0.5.0.dist-info/LICENSE
settingscascade-0.5.0.dist-info/WHEEL
settingscascade-0.5.0.dist-info/METADATA
settingscascade-0.5.0.dist-info/RECORD
