Metadata-Version: 2.1
Name: settingscascade
Version: 0.5.0
Summary: Cascade settings from multiple levels of specificity
Home-page: https://gitlab.com/pjbecotte/settingscascade
License: MIT
Keywords: config,settings,ini,css,specificity
Author: Paul Becotte
Author-email: pjbecotte@gmail.com
Requires-Python: >=3.6,<4.0
Classifier: Development Status :: 4 - Beta
Classifier: Intended Audience :: Developers
Classifier: License :: OSI Approved :: MIT License
Classifier: Programming Language :: Python :: 3
Classifier: Programming Language :: Python :: 3.6
Classifier: Programming Language :: Python :: 3.7
Classifier: Programming Language :: Python :: 3.8
Classifier: Topic :: Software Development :: Libraries
Requires-Dist: jinja2 (>=2.10,<2.11)
Requires-Dist: sortedcontainers (>=2.1,<2.2)
Project-URL: Repository, https://gitlab.com/pjbecotte/settingscascade
